<?xml version="1.0" encoding="utf-8"?>
<doctrine-mapping xmlns="http://doctrine-project.org/schemas/orm/doctrine-mapping" xmlns:xsi="http://www.w3.org/2001/XMLSchema-instance" xsi:schemaLocation="http://doctrine-project.org/schemas/orm/doctrine-mapping http://doctrine-project.org/schemas/orm/doctrine-mapping.xsd">
  <entity name="Saia\FtContratoLaboral" table="ft_contrato_laboral">
    <indexes>
      <index name="i_ft_contrato_laboral_doc" columns="documento_iddocumento"/>
      <index name="i_contrato_laboral_hoja_vida" columns="ft_hoja_vida"/>
      <index name="i_contrato_laboral_serie_idse" columns="serie_idserie"/>
    </indexes>
    <id name="idftContratoLaboral" type="integer" column="idft_contrato_laboral">
      <generator strategy="IDENTITY"/>
    </id>
    <field name="encabezado" type="integer" column="encabezado" nullable="false">
      <options>
        <option name="unsigned"/>
        <option name="default">1</option>
      </options>
    </field>
    <field name="firma" type="integer" column="firma" nullable="false">
      <options>
        <option name="unsigned"/>
        <option name="default">1</option>
      </options>
    </field>
    <field name="tipoContrato" type="integer" column="tipo_contrato" nullable="false">
      <options>
        <option name="unsigned"/>
      </options>
    </field>
    <field name="numContarto" type="string" column="num_contarto" length="255" nullable="false">
      <options>
        <option name="fixed"/>
      </options>
    </field>
    <field name="fechaFinal" type="date" column="fecha_final" nullable="false"/>
    <field name="fechaInicio" type="date" column="fecha_inicio" nullable="false"/>
    <field name="serieIdserie" type="integer" column="serie_idserie" nullable="false">
      <options>
        <option name="unsigned"/>
        <option name="default">897</option>
      </options>
    </field>
    <field name="ftHojaVida" type="integer" column="ft_hoja_vida" nullable="false">
      <options>
        <option name="unsigned"/>
      </options>
    </field>
    <field name="dependencia" type="integer" column="dependencia" nullable="false">
      <options>
        <option name="unsigned"/>
      </options>
    </field>
    <field name="documentoIddocumento" type="integer" column="documento_iddocumento" nullable="false">
      <options>
        <option name="unsigned"/>
      </options>
    </field>
    <field name="adjuntarDocumento" type="string" column="adjuntar_documento" length="255" nullable="true">
      <options>
        <option name="fixed"/>
      </options>
    </field>
    <field name="sueldoFinal" type="string" column="sueldo_final" length="255" nullable="true">
      <options>
        <option name="fixed"/>
      </options>
    </field>
    <field name="sueldoIni" type="string" column="sueldo_ini" length="255" nullable="true">
      <options>
        <option name="fixed"/>
      </options>
    </field>
    <field name="estadoDocumento" type="integer" column="estado_documento" nullable="false">
      <options>
        <option name="unsigned"/>
        <option name="default">1</option>
      </options>
    </field>
  </entity>
</doctrine-mapping>
