<?xml version="1.0" encoding="utf-8"?>
<doctrine-mapping xmlns="http://doctrine-project.org/schemas/orm/doctrine-mapping" xmlns:xsi="http://www.w3.org/2001/XMLSchema-instance" xsi:schemaLocation="http://doctrine-project.org/schemas/orm/doctrine-mapping http://doctrine-project.org/schemas/orm/doctrine-mapping.xsd">
  <entity name="Saia\CategoriaFormato" table="categoria_formato">
    <id name="idcategoriaFormato" type="integer" column="idcategoria_formato">
      <generator strategy="IDENTITY"/>
    </id>
    <field name="nombre" type="string" column="nombre" length="255" nullable="false">
      <options>
        <option name="fixed"/>
      </options>
    </field>
    <field name="codPadre" type="integer" column="cod_padre" nullable="true">
      <options>
        <option name="unsigned"/>
      </options>
    </field>
    <field name="estado" type="integer" column="estado" nullable="false">
      <options>
        <option name="unsigned"/>
        <option name="comment">1,Activo;2,Inactivo</option>
      </options>
    </field>
    <field name="descripcion" type="text" column="descripcion" length="65535" nullable="true">
      <options>
        <option name="fixed"/>
      </options>
    </field>
    <field name="fecha" type="date" column="fecha" nullable="true"/>
  </entity>
</doctrine-mapping>
