<?xml version="1.0" encoding="utf-8"?>
<doctrine-mapping xmlns="http://doctrine-project.org/schemas/orm/doctrine-mapping" xmlns:xsi="http://www.w3.org/2001/XMLSchema-instance" xsi:schemaLocation="http://doctrine-project.org/schemas/orm/doctrine-mapping http://doctrine-project.org/schemas/orm/doctrine-mapping.xsd">
  <entity name="Saia\FtExperienciaLaboral" table="ft_experiencia_laboral">
    <indexes>
      <index name="i_ft_experiencia_laboral_doc" columns="documento_iddocumento"/>
      <index name="i_experiencia_laboral_hoja_vida" columns="ft_hoja_vida"/>
      <index name="i_experiencia_laboral_serie_idse" columns="serie_idserie"/>
    </indexes>
    <id name="idftExperienciaLaboral" type="integer" column="idft_experiencia_laboral">
      <generator strategy="IDENTITY"/>
    </id>
    <field name="serieIdserie" type="integer" column="serie_idserie" nullable="false">
      <options>
        <option name="unsigned"/>
        <option name="default">891</option>
      </options>
    </field>
    <field name="adjuntarDocumento" type="string" column="adjuntar_documento" length="255" nullable="true">
      <options>
        <option name="fixed"/>
      </options>
    </field>
    <field name="cargoRealizado" type="string" column="cargo_realizado" length="255" nullable="false">
      <options>
        <option name="fixed"/>
      </options>
    </field>
    <field name="direccion" type="string" column="direccion" length="255" nullable="true">
      <options>
        <option name="fixed"/>
      </options>
    </field>
    <field name="fechaIngreso" type="date" column="fecha_ingreso" nullable="false"/>
    <field name="fechaRetiro" type="date" column="fecha_retiro" nullable="true"/>
    <field name="ftHojaVida" type="integer" column="ft_hoja_vida" nullable="false">
      <options>
        <option name="unsigned"/>
      </options>
    </field>
    <field name="funcionesRealizadas" type="text" column="funciones_realizadas" length="65535" nullable="true">
      <options>
        <option name="fixed"/>
      </options>
    </field>
    <field name="jefeInmediato" type="string" column="jefe_inmediato" length="255" nullable="true">
      <options>
        <option name="fixed"/>
      </options>
    </field>
    <field name="motivoRetiro" type="text" column="motivo_retiro" length="65535" nullable="true">
      <options>
        <option name="fixed"/>
      </options>
    </field>
    <field name="nombre" type="string" column="nombre" length="255" nullable="true">
      <options>
        <option name="fixed"/>
      </options>
    </field>
    <field name="salarioFinal" type="string" column="salario_final" length="255" nullable="true">
      <options>
        <option name="fixed"/>
      </options>
    </field>
    <field name="salarioInicial" type="string" column="salario_inicial" length="100" nullable="true">
      <options>
        <option name="fixed"/>
      </options>
    </field>
    <field name="telefonos" type="string" column="telefonos" length="255" nullable="true">
      <options>
        <option name="fixed"/>
      </options>
    </field>
    <field name="documentoIddocumento" type="integer" column="documento_iddocumento" nullable="false">
      <options>
        <option name="unsigned"/>
      </options>
    </field>
    <field name="dependencia" type="integer" column="dependencia" nullable="false">
      <options>
        <option name="unsigned"/>
      </options>
    </field>
    <field name="encabezado" type="integer" column="encabezado" nullable="false">
      <options>
        <option name="unsigned"/>
        <option name="default">1</option>
      </options>
    </field>
    <field name="firma" type="integer" column="firma" nullable="false">
      <options>
        <option name="unsigned"/>
        <option name="default">1</option>
      </options>
    </field>
    <field name="nombreEmpresa" type="string" column="nombre_empresa" length="255" nullable="false">
      <options>
        <option name="fixed"/>
      </options>
    </field>
    <field name="verificado" type="integer" column="verificado" nullable="true">
      <options>
        <option name="unsigned"/>
      </options>
    </field>
    <field name="estadoDocumento" type="integer" column="estado_documento" nullable="false">
      <options>
        <option name="unsigned"/>
        <option name="default">1</option>
      </options>
    </field>
  </entity>
</doctrine-mapping>
